{"cameraMode":{"drawMode":0,"name":"Shaded","section":"Shading Mode"},"sceneLighting":true,"audioPlay":false,"sceneViewState":{"m_AlwaysRefresh":false,"showFog":true,"showSkybox":true,"showFlares":true,"showImageEffects":true,"showParticleSystems":true,"showVisualEffectGraphs":true,"m_FxEnabled":true},"in2DMode":false,"pivot":{"x":267.9516296386719,"y":321.20306396484377,"z":-170.11996459960938},"rotation":{"x":0.31458184123039248,"y":-0.3790372312068939,"z":0.13878901302814485,"w":0.8591322898864746},"size":23.32172966003418,"orthographic":false}